[
  {"placement_id": 1447, "mirrored_placement_id": null, "x": 140, "y": 4},
  {"placement_id": 1073, "mirrored_placement_id": null, "x": 136, "y": 8},
  {"placement_id": 1448, "mirrored_placement_id": null, "x": 132, "y": 4},
  {"placement_id": 1074, "mirrored_placement_id": null, "x": 128, "y": 8},
  {"placement_id": 1449, "mirrored_placement_id": null, "x": 124, "y": 4},
  {"placement_id": 1075, "mirrored_placement_id": null, "x": 120, "y": 8},
  {"placement_id": 1450, "mirrored_placement_id": null, "x": 116, "y": 4},
  {"placement_id": 1076, "mirrored_placement_id": null, "x": 112, "y": 8},
  {"placement_id": 1451, "mirrored_placement_id": null, "x": 108, "y": 4},
  {"placement_id": 1077, "mirrored_placement_id": null, "x": 104, "y": 8},
  {"placement_id": 1452, "mirrored_placement_id": null, "x": 100, "y": 4},
  {"placement_id": 1078, "mirrored_placement_id": null, "x": 96, "y": 8},
  {"placement_id": 1453, "mirrored_placement_id": null, "x": 92, "y": 4},
  {"placement_id": 1079, "mirrored_placement_id": null, "x": 88, "y": 8},
  {"placement_id": 1454, "mirrored_placement_id": null, "x": 84, "y": 4},
  {"placement_id": 1080, "mirrored_placement_id": null, "x": 80, "y": 8},
  {"placement_id": 1455, "mirrored_placement_id": null, "x": 76, "y": 4},
  {"placement_id": 1081, "mirrored_placement_id": null, "x": 72, "y": 8},
  {"placement_id": 1456, "mirrored_placement_id": null, "x": 68, "y": 4},
  {"placement_id": 1082, "mirrored_placement_id": null, "x": 64, "y": 8},
  {"placement_id": 1457, "mirrored_placement_id": null, "x": 60, "y": 4},
  {"placement_id": 1083, "mirrored_placement_id": null, "x": 56, "y": 8},
  {"placement_id": 1458, "mirrored_placement_id": null, "x": 52, "y": 4},
  {"placement_id": 1084, "mirrored_placement_id": null, "x": 48, "y": 8},
  {"placement_id": 1459, "mirrored_placement_id": null, "x": 44, "y": 4},
  {"placement_id": 1085, "mirrored_placement_id": null, "x": 40, "y": 8},
  {"placement_id": 1460, "mirrored_placement_id": null, "x": 36, "y": 4},
  {"placement_id": 1086, "mirrored_placement_id": null, "x": 32, "y": 8},
  {"placement_id": 1461, "mirrored_placement_id": null, "x": 28, "y": 4},
  {"placement_id": 1087, "mirrored_placement_id": null, "x": 24, "y": 8},
  {"placement_id": 1462, "mirrored_placement_id": null, "x": 20, "y": 4},
  {"placement_id": 1088, "mirrored_placement_id": null, "x": 16, "y": 8},
  {"placement_id": 1463, "mirrored_placement_id": null, "x": 12, "y": 4},
  {"placement_id": 1464, "mirrored_placement_id": null, "x": 4, "y": 4},
  {"placement_id": 1089, "mirrored_placement_id": null, "x": 8, "y": 8},
  {"placement_id": 1090, "mirrored_placement_id": null, "x": 8, "y": 16},
  {"placement_id": 1465, "mirrored_placement_id": null, "x": 4, "y": 20},
  {"placement_id": 1107, "mirrored_placement_id": null, "x": 8, "y": 24},
  {"placement_id": 1474, "mirrored_placement_id": null, "x": 12, "y": 28},
  {"placement_id": 1124, "mirrored_placement_id": null, "x": 8, "y": 32},
  {"placement_id": 1483, "mirrored_placement_id": null, "x": 4, "y": 36},
  {"placement_id": 1141, "mirrored_placement_id": null, "x": 8, "y": 40},
  {"placement_id": 1492, "mirrored_placement_id": null, "x": 12, "y": 44},
  {"placement_id": 1158, "mirrored_placement_id": null, "x": 8, "y": 48},
  {"placement_id": 1501, "mirrored_placement_id": null, "x": 4, "y": 52},
  {"placement_id": 1175, "mirrored_placement_id": null, "x": 8, "y": 56},
  {"placement_id": 1510, "mirrored_placement_id": null, "x": 12, "y": 60},
  {"placement_id": 1192, "mirrored_placement_id": null, "x": 8, "y": 64},
  {"placement_id": 1519, "mirrored_placement_id": null, "x": 4, "y": 68},
  {"placement_id": 1209, "mirrored_placement_id": null, "x": 8, "y": 72},
  {"placement_id": 1528, "mirrored_placement_id": null, "x": 12, "y": 76},
  {"placement_id": 1226, "mirrored_placement_id": null, "x": 8, "y": 80},
  {"placement_id": 1537, "mirrored_placement_id": null, "x": 4, "y": 84},
  {"placement_id": 1243, "mirrored_placement_id": null, "x": 8, "y": 88},
  {"placement_id": 1546, "mirrored_placement_id": null, "x": 12, "y": 92},
  {"placement_id": 1260, "mirrored_placement_id": null, "x": 8, "y": 96},
  {"placement_id": 1555, "mirrored_placement_id": null, "x": 4, "y": 100},
  {"placement_id": 1277, "mirrored_placement_id": null, "x": 8, "y": 104},
  {"placement_id": 1564, "mirrored_placement_id": null, "x": 12, "y": 108},
  {"placement_id": 1294, "mirrored_placement_id": null, "x": 8, "y": 112},
  {"placement_id": 1573, "mirrored_placement_id": null, "x": 4, "y": 116},
  {"placement_id": 1311, "mirrored_placement_id": null, "x": 8, "y": 120},
  {"placement_id": 1582, "mirrored_placement_id": null, "x": 12, "y": 124},
  {"placement_id": 1328, "mirrored_placement_id": null, "x": 8, "y": 128},
  {"placement_id": 1591, "mirrored_placement_id": null, "x": 4, "y": 132},
  {"placement_id": 1345, "mirrored_placement_id": null, "x": 8, "y": 136},
  {"placement_id": 1362, "mirrored_placement_id": null, "x": 8, "y": 144},
  {"placement_id": 1379, "mirrored_placement_id": null, "x": 8, "y": 152},
  {"placement_id": 1396, "mirrored_placement_id": null, "x": 8, "y": 160},
  {"placement_id": 1413, "mirrored_placement_id": null, "x": 8, "y": 168},
  {"placement_id": 1430, "mirrored_placement_id": null, "x": 8, "y": 176},
  {"placement_id": 1431, "mirrored_placement_id": null, "x": 16, "y": 176},
  {"placement_id": 1414, "mirrored_placement_id": null, "x": 16, "y": 168},
  {"placement_id": 1397, "mirrored_placement_id": null, "x": 16, "y": 160},
  {"placement_id": 1380, "mirrored_placement_id": null, "x": 16, "y": 152},
  {"placement_id": 1363, "mirrored_placement_id": null, "x": 16, "y": 144},
  {"placement_id": 1346, "mirrored_placement_id": null, "x": 16, "y": 136},
  {"placement_id": 1592, "mirrored_placement_id": null, "x": 20, "y": 132},
  {"placement_id": 1329, "mirrored_placement_id": null, "x": 16, "y": 128},
  {"placement_id": 1312, "mirrored_placement_id": null, "x": 16, "y": 120},
  {"placement_id": 1574, "mirrored_placement_id": null, "x": 20, "y": 116},
  {"placement_id": 1295, "mirrored_placement_id": null, "x": 16, "y": 112},
  {"placement_id": 1278, "mirrored_placement_id": null, "x": 16, "y": 104},
  {"placement_id": 1556, "mirrored_placement_id": null, "x": 20, "y": 100},
  {"placement_id": 1261, "mirrored_placement_id": null, "x": 16, "y": 96},
  {"placement_id": 1244, "mirrored_placement_id": null, "x": 16, "y": 88},
  {"placement_id": 1538, "mirrored_placement_id": null, "x": 20, "y": 84},
  {"placement_id": 1227, "mirrored_placement_id": null, "x": 16, "y": 80},
  {"placement_id": 1210, "mirrored_placement_id": null, "x": 16, "y": 72},
  {"placement_id": 1520, "mirrored_placement_id": null, "x": 20, "y": 68},
  {"placement_id": 1193, "mirrored_placement_id": null, "x": 16, "y": 64},
  {"placement_id": 1176, "mirrored_placement_id": null, "x": 16, "y": 56},
  {"placement_id": 1502, "mirrored_placement_id": null, "x": 20, "y": 52},
  {"placement_id": 1159, "mirrored_placement_id": null, "x": 16, "y": 48},
  {"placement_id": 1142, "mirrored_placement_id": null, "x": 16, "y": 40},
  {"placement_id": 1484, "mirrored_placement_id": null, "x": 20, "y": 36},
  {"placement_id": 1125, "mirrored_placement_id": null, "x": 16, "y": 32},
  {"placement_id": 1108, "mirrored_placement_id": null, "x": 16, "y": 24},
  {"placement_id": 1466, "mirrored_placement_id": null, "x": 20, "y": 20},
  {"placement_id": 1091, "mirrored_placement_id": null, "x": 16, "y": 16},
  {"placement_id": 1092, "mirrored_placement_id": null, "x": 24, "y": 16},
  {"placement_id": 1109, "mirrored_placement_id": null, "x": 24, "y": 24},
  {"placement_id": 1475, "mirrored_placement_id": null, "x": 28, "y": 28},
  {"placement_id": 1126, "mirrored_placement_id": null, "x": 24, "y": 32},
  {"placement_id": 1143, "mirrored_placement_id": null, "x": 24, "y": 40},
  {"placement_id": 1493, "mirrored_placement_id": null, "x": 28, "y": 44},
  {"placement_id": 1160, "mirrored_placement_id": null, "x": 24, "y": 48},
  {"placement_id": 1177, "mirrored_placement_id": null, "x": 24, "y": 56},
  {"placement_id": 1511, "mirrored_placement_id": null, "x": 28, "y": 60},
  {"placement_id": 1194, "mirrored_placement_id": null, "x": 24, "y": 64},
  {"placement_id": 1211, "mirrored_placement_id": null, "x": 24, "y": 72},
  {"placement_id": 1529, "mirrored_placement_id": null, "x": 28, "y": 76},
  {"placement_id": 1228, "mirrored_placement_id": null, "x": 24, "y": 80},
  {"placement_id": 1245, "mirrored_placement_id": null, "x": 24, "y": 88},
  {"placement_id": 1547, "mirrored_placement_id": null, "x": 28, "y": 92},
  {"placement_id": 1262, "mirrored_placement_id": null, "x": 24, "y": 96},
  {"placement_id": 1279, "mirrored_placement_id": null, "x": 24, "y": 104},
  {"placement_id": 1565, "mirrored_placement_id": null, "x": 28, "y": 108},
  {"placement_id": 1296, "mirrored_placement_id": null, "x": 24, "y": 112},
  {"placement_id": 1313, "mirrored_placement_id": null, "x": 24, "y": 120},
  {"placement_id": 1583, "mirrored_placement_id": null, "x": 28, "y": 124},
  {"placement_id": 1330, "mirrored_placement_id": null, "x": 24, "y": 128},
  {"placement_id": 1347, "mirrored_placement_id": null, "x": 24, "y": 136},
  {"placement_id": 1364, "mirrored_placement_id": null, "x": 24, "y": 144},
  {"placement_id": 1381, "mirrored_placement_id": null, "x": 24, "y": 152},
  {"placement_id": 1398, "mirrored_placement_id": null, "x": 24, "y": 160},
  {"placement_id": 1415, "mirrored_placement_id": null, "x": 24, "y": 168},
  {"placement_id": 1432, "mirrored_placement_id": null, "x": 24, "y": 176},
  {"placement_id": 1433, "mirrored_placement_id": null, "x": 32, "y": 176},
  {"placement_id": 1416, "mirrored_placement_id": null, "x": 32, "y": 168},
  {"placement_id": 1399, "mirrored_placement_id": null, "x": 32, "y": 160},
  {"placement_id": 1382, "mirrored_placement_id": null, "x": 32, "y": 152},
  {"placement_id": 1365, "mirrored_placement_id": null, "x": 32, "y": 144},
  {"placement_id": 1348, "mirrored_placement_id": null, "x": 32, "y": 136},
  {"placement_id": 1593, "mirrored_placement_id": null, "x": 36, "y": 132},
  {"placement_id": 1331, "mirrored_placement_id": null, "x": 32, "y": 128},
  {"placement_id": 1314, "mirrored_placement_id": null, "x": 32, "y": 120},
  {"placement_id": 1575, "mirrored_placement_id": null, "x": 36, "y": 116},
  {"placement_id": 1297, "mirrored_placement_id": null, "x": 32, "y": 112},
  {"placement_id": 1280, "mirrored_placement_id": null, "x": 32, "y": 104},
  {"placement_id": 1557, "mirrored_placement_id": null, "x": 36, "y": 100},
  {"placement_id": 1263, "mirrored_placement_id": null, "x": 32, "y": 96},
  {"placement_id": 1246, "mirrored_placement_id": null, "x": 32, "y": 88},
  {"placement_id": 1539, "mirrored_placement_id": null, "x": 36, "y": 84},
  {"placement_id": 1229, "mirrored_placement_id": null, "x": 32, "y": 80},
  {"placement_id": 1212, "mirrored_placement_id": null, "x": 32, "y": 72},
  {"placement_id": 1521, "mirrored_placement_id": null, "x": 36, "y": 68},
  {"placement_id": 1195, "mirrored_placement_id": null, "x": 32, "y": 64},
  {"placement_id": 1178, "mirrored_placement_id": null, "x": 32, "y": 56},
  {"placement_id": 1503, "mirrored_placement_id": null, "x": 36, "y": 52},
  {"placement_id": 1161, "mirrored_placement_id": null, "x": 32, "y": 48},
  {"placement_id": 1144, "mirrored_placement_id": null, "x": 32, "y": 40},
  {"placement_id": 1485, "mirrored_placement_id": null, "x": 36, "y": 36},
  {"placement_id": 1127, "mirrored_placement_id": null, "x": 32, "y": 32},
  {"placement_id": 1110, "mirrored_placement_id": null, "x": 32, "y": 24},
  {"placement_id": 1468, "mirrored_placement_id": null, "x": 52, "y": 20},
  {"placement_id": 1095, "mirrored_placement_id": null, "x": 48, "y": 16},
  {"placement_id": 1096, "mirrored_placement_id": null, "x": 56, "y": 16},
  {"placement_id": 1113, "mirrored_placement_id": null, "x": 56, "y": 24},
  {"placement_id": 1477, "mirrored_placement_id": null, "x": 60, "y": 28},
  {"placement_id": 1130, "mirrored_placement_id": null, "x": 56, "y": 32},
  {"placement_id": 1147, "mirrored_placement_id": null, "x": 56, "y": 40},
  {"placement_id": 1495, "mirrored_placement_id": null, "x": 60, "y": 44},
  {"placement_id": 1164, "mirrored_placement_id": null, "x": 56, "y": 48},
  {"placement_id": 1181, "mirrored_placement_id": null, "x": 56, "y": 56},
  {"placement_id": 1513, "mirrored_placement_id": null, "x": 60, "y": 60},
  {"placement_id": 1198, "mirrored_placement_id": null, "x": 56, "y": 64},
  {"placement_id": 1215, "mirrored_placement_id": null, "x": 56, "y": 72},
  {"placement_id": 1531, "mirrored_placement_id": null, "x": 60, "y": 76},
  {"placement_id": 1232, "mirrored_placement_id": null, "x": 56, "y": 80},
  {"placement_id": 1249, "mirrored_placement_id": null, "x": 56, "y": 88},
  {"placement_id": 1549, "mirrored_placement_id": null, "x": 60, "y": 92},
  {"placement_id": 1266, "mirrored_placement_id": null, "x": 56, "y": 96},
  {"placement_id": 1283, "mirrored_placement_id": null, "x": 56, "y": 104},
  {"placement_id": 1567, "mirrored_placement_id": null, "x": 60, "y": 108},
  {"placement_id": 1300, "mirrored_placement_id": null, "x": 56, "y": 112},
  {"placement_id": 1317, "mirrored_placement_id": null, "x": 56, "y": 120},
  {"placement_id": 1585, "mirrored_placement_id": null, "x": 60, "y": 124},
  {"placement_id": 1334, "mirrored_placement_id": null, "x": 56, "y": 128},
  {"placement_id": 1351, "mirrored_placement_id": null, "x": 56, "y": 136},
  {"placement_id": 1368, "mirrored_placement_id": null, "x": 56, "y": 144},
  {"placement_id": 1385, "mirrored_placement_id": null, "x": 56, "y": 152},
  {"placement_id": 1402, "mirrored_placement_id": null, "x": 56, "y": 160},
  {"placement_id": 1419, "mirrored_placement_id": null, "x": 56, "y": 168},
  {"placement_id": 1436, "mirrored_placement_id": null, "x": 56, "y": 176},
  {"placement_id": 1437, "mirrored_placement_id": null, "x": 64, "y": 176},
  {"placement_id": 1420, "mirrored_placement_id": null, "x": 64, "y": 168},
  {"placement_id": 1403, "mirrored_placement_id": null, "x": 64, "y": 160},
  {"placement_id": 1386, "mirrored_placement_id": null, "x": 64, "y": 152},
  {"placement_id": 1369, "mirrored_placement_id": null, "x": 64, "y": 144},
  {"placement_id": 1352, "mirrored_placement_id": null, "x": 64, "y": 136},
  {"placement_id": 1595, "mirrored_placement_id": null, "x": 68, "y": 132},
  {"placement_id": 1335, "mirrored_placement_id": null, "x": 64, "y": 128},
  {"placement_id": 1318, "mirrored_placement_id": null, "x": 64, "y": 120},
  {"placement_id": 1577, "mirrored_placement_id": null, "x": 68, "y": 116},
  {"placement_id": 1301, "mirrored_placement_id": null, "x": 64, "y": 112},
  {"placement_id": 1284, "mirrored_placement_id": null, "x": 64, "y": 104},
  {"placement_id": 1559, "mirrored_placement_id": null, "x": 68, "y": 100},
  {"placement_id": 1267, "mirrored_placement_id": null, "x": 64, "y": 96},
  {"placement_id": 1250, "mirrored_placement_id": null, "x": 64, "y": 88},
  {"placement_id": 1541, "mirrored_placement_id": null, "x": 68, "y": 84},
  {"placement_id": 1233, "mirrored_placement_id": null, "x": 64, "y": 80},
  {"placement_id": 1216, "mirrored_placement_id": null, "x": 64, "y": 72},
  {"placement_id": 1523, "mirrored_placement_id": null, "x": 68, "y": 68},
  {"placement_id": 1199, "mirrored_placement_id": null, "x": 64, "y": 64},
  {"placement_id": 1182, "mirrored_placement_id": null, "x": 64, "y": 56},
  {"placement_id": 1505, "mirrored_placement_id": null, "x": 68, "y": 52},
  {"placement_id": 1165, "mirrored_placement_id": null, "x": 64, "y": 48},
  {"placement_id": 1148, "mirrored_placement_id": null, "x": 64, "y": 40},
  {"placement_id": 1487, "mirrored_placement_id": null, "x": 68, "y": 36},
  {"placement_id": 1131, "mirrored_placement_id": null, "x": 64, "y": 32},
  {"placement_id": 1114, "mirrored_placement_id": null, "x": 64, "y": 24},
  {"placement_id": 1469, "mirrored_placement_id": null, "x": 68, "y": 20},
  {"placement_id": 1097, "mirrored_placement_id": null, "x": 64, "y": 16},
  {"placement_id": 1098, "mirrored_placement_id": null, "x": 72, "y": 16},
  {"placement_id": 1115, "mirrored_placement_id": null, "x": 72, "y": 24},
  {"placement_id": 1478, "mirrored_placement_id": null, "x": 76, "y": 28},
  {"placement_id": 1132, "mirrored_placement_id": null, "x": 72, "y": 32},
  {"placement_id": 1149, "mirrored_placement_id": null, "x": 72, "y": 40},
  {"placement_id": 1496, "mirrored_placement_id": null, "x": 76, "y": 44},
  {"placement_id": 1166, "mirrored_placement_id": null, "x": 72, "y": 48},
  {"placement_id": 1183, "mirrored_placement_id": null, "x": 72, "y": 56},
  {"placement_id": 1514, "mirrored_placement_id": null, "x": 76, "y": 60},
  {"placement_id": 1200, "mirrored_placement_id": null, "x": 72, "y": 64},
  {"placement_id": 1217, "mirrored_placement_id": null, "x": 72, "y": 72},
  {"placement_id": 1532, "mirrored_placement_id": null, "x": 76, "y": 76},
  {"placement_id": 1234, "mirrored_placement_id": null, "x": 72, "y": 80},
  {"placement_id": 1251, "mirrored_placement_id": null, "x": 72, "y": 88},
  {"placement_id": 1550, "mirrored_placement_id": null, "x": 76, "y": 92},
  {"placement_id": 1268, "mirrored_placement_id": null, "x": 72, "y": 96},
  {"placement_id": 1285, "mirrored_placement_id": null, "x": 72, "y": 104},
  {"placement_id": 1568, "mirrored_placement_id": null, "x": 76, "y": 108},
  {"placement_id": 1302, "mirrored_placement_id": null, "x": 72, "y": 112},
  {"placement_id": 1319, "mirrored_placement_id": null, "x": 72, "y": 120},
  {"placement_id": 1586, "mirrored_placement_id": null, "x": 76, "y": 124},
  {"placement_id": 1336, "mirrored_placement_id": null, "x": 72, "y": 128},
  {"placement_id": 1353, "mirrored_placement_id": null, "x": 72, "y": 136},
  {"placement_id": 1370, "mirrored_placement_id": null, "x": 72, "y": 144},
  {"placement_id": 1387, "mirrored_placement_id": null, "x": 72, "y": 152},
  {"placement_id": 1404, "mirrored_placement_id": null, "x": 72, "y": 160},
  {"placement_id": 1421, "mirrored_placement_id": null, "x": 72, "y": 168},
  {"placement_id": 1438, "mirrored_placement_id": null, "x": 72, "y": 176},
  {"placement_id": 1439, "mirrored_placement_id": null, "x": 80, "y": 176},
  {"placement_id": 1422, "mirrored_placement_id": null, "x": 80, "y": 168},
  {"placement_id": 1405, "mirrored_placement_id": null, "x": 80, "y": 160},
  {"placement_id": 1388, "mirrored_placement_id": null, "x": 80, "y": 152},
  {"placement_id": 1371, "mirrored_placement_id": null, "x": 80, "y": 144},
  {"placement_id": 1354, "mirrored_placement_id": null, "x": 80, "y": 136},
  {"placement_id": 1596, "mirrored_placement_id": null, "x": 84, "y": 132},
  {"placement_id": 1337, "mirrored_placement_id": null, "x": 80, "y": 128},
  {"placement_id": 1320, "mirrored_placement_id": null, "x": 80, "y": 120},
  {"placement_id": 1578, "mirrored_placement_id": null, "x": 84, "y": 116},
  {"placement_id": 1303, "mirrored_placement_id": null, "x": 80, "y": 112},
  {"placement_id": 1286, "mirrored_placement_id": null, "x": 80, "y": 104},
  {"placement_id": 1560, "mirrored_placement_id": null, "x": 84, "y": 100},
  {"placement_id": 1269, "mirrored_placement_id": null, "x": 80, "y": 96},
  {"placement_id": 1252, "mirrored_placement_id": null, "x": 80, "y": 88},
  {"placement_id": 1542, "mirrored_placement_id": null, "x": 84, "y": 84},
  {"placement_id": 1235, "mirrored_placement_id": null, "x": 80, "y": 80},
  {"placement_id": 1218, "mirrored_placement_id": null, "x": 80, "y": 72},
  {"placement_id": 1524, "mirrored_placement_id": null, "x": 84, "y": 68},
  {"placement_id": 1201, "mirrored_placement_id": null, "x": 80, "y": 64},
  {"placement_id": 1184, "mirrored_placement_id": null, "x": 80, "y": 56},
  {"placement_id": 1506, "mirrored_placement_id": null, "x": 84, "y": 52},
  {"placement_id": 1167, "mirrored_placement_id": null, "x": 80, "y": 48},
  {"placement_id": 1150, "mirrored_placement_id": null, "x": 80, "y": 40},
  {"placement_id": 1488, "mirrored_placement_id": null, "x": 84, "y": 36},
  {"placement_id": 1133, "mirrored_placement_id": null, "x": 80, "y": 32},
  {"placement_id": 1116, "mirrored_placement_id": null, "x": 80, "y": 24},
  {"placement_id": 1470, "mirrored_placement_id": null, "x": 84, "y": 20},
  {"placement_id": 1099, "mirrored_placement_id": null, "x": 80, "y": 16},
  {"placement_id": 1100, "mirrored_placement_id": null, "x": 88, "y": 16},
  {"placement_id": 1117, "mirrored_placement_id": null, "x": 88, "y": 24},
  {"placement_id": 1479, "mirrored_placement_id": null, "x": 92, "y": 28},
  {"placement_id": 1134, "mirrored_placement_id": null, "x": 88, "y": 32},
  {"placement_id": 1151, "mirrored_placement_id": null, "x": 88, "y": 40},
  {"placement_id": 1497, "mirrored_placement_id": null, "x": 92, "y": 44},
  {"placement_id": 1168, "mirrored_placement_id": null, "x": 88, "y": 48},
  {"placement_id": 1185, "mirrored_placement_id": null, "x": 88, "y": 56},
  {"placement_id": 1515, "mirrored_placement_id": null, "x": 92, "y": 60},
  {"placement_id": 1202, "mirrored_placement_id": null, "x": 88, "y": 64},
  {"placement_id": 1219, "mirrored_placement_id": null, "x": 88, "y": 72},
  {"placement_id": 1533, "mirrored_placement_id": null, "x": 92, "y": 76},
  {"placement_id": 1236, "mirrored_placement_id": null, "x": 88, "y": 80},
  {"placement_id": 1253, "mirrored_placement_id": null, "x": 88, "y": 88},
  {"placement_id": 1551, "mirrored_placement_id": null, "x": 92, "y": 92},
  {"placement_id": 1270, "mirrored_placement_id": null, "x": 88, "y": 96},
  {"placement_id": 1287, "mirrored_placement_id": null, "x": 88, "y": 104},
  {"placement_id": 1569, "mirrored_placement_id": null, "x": 92, "y": 108},
  {"placement_id": 1304, "mirrored_placement_id": null, "x": 88, "y": 112},
  {"placement_id": 1321, "mirrored_placement_id": null, "x": 88, "y": 120},
  {"placement_id": 1587, "mirrored_placement_id": null, "x": 92, "y": 124},
  {"placement_id": 1338, "mirrored_placement_id": null, "x": 88, "y": 128},
  {"placement_id": 1355, "mirrored_placement_id": null, "x": 88, "y": 136},
  {"placement_id": 1372, "mirrored_placement_id": null, "x": 88, "y": 144},
  {"placement_id": 1389, "mirrored_placement_id": null, "x": 88, "y": 152},
  {"placement_id": 1406, "mirrored_placement_id": null, "x": 88, "y": 160},
  {"placement_id": 1423, "mirrored_placement_id": null, "x": 88, "y": 168},
  {"placement_id": 1440, "mirrored_placement_id": null, "x": 88, "y": 176},
  {"placement_id": 1441, "mirrored_placement_id": null, "x": 96, "y": 176},
  {"placement_id": 1424, "mirrored_placement_id": null, "x": 96, "y": 168},
  {"placement_id": 1407, "mirrored_placement_id": null, "x": 96, "y": 160},
  {"placement_id": 1390, "mirrored_placement_id": null, "x": 96, "y": 152},
  {"placement_id": 1373, "mirrored_placement_id": null, "x": 96, "y": 144},
  {"placement_id": 1356, "mirrored_placement_id": null, "x": 96, "y": 136},
  {"placement_id": 1597, "mirrored_placement_id": null, "x": 100, "y": 132},
  {"placement_id": 1339, "mirrored_placement_id": null, "x": 96, "y": 128},
  {"placement_id": 1322, "mirrored_placement_id": null, "x": 96, "y": 120},
  {"placement_id": 1579, "mirrored_placement_id": null, "x": 100, "y": 116},
  {"placement_id": 1305, "mirrored_placement_id": null, "x": 96, "y": 112},
  {"placement_id": 1288, "mirrored_placement_id": null, "x": 96, "y": 104},
  {"placement_id": 1561, "mirrored_placement_id": null, "x": 100, "y": 100},
  {"placement_id": 1271, "mirrored_placement_id": null, "x": 96, "y": 96},
  {"placement_id": 1254, "mirrored_placement_id": null, "x": 96, "y": 88},
  {"placement_id": 1543, "mirrored_placement_id": null, "x": 100, "y": 84},
  {"placement_id": 1237, "mirrored_placement_id": null, "x": 96, "y": 80},
  {"placement_id": 1220, "mirrored_placement_id": null, "x": 96, "y": 72},
  {"placement_id": 1525, "mirrored_placement_id": null, "x": 100, "y": 68},
  {"placement_id": 1203, "mirrored_placement_id": null, "x": 96, "y": 64},
  {"placement_id": 1186, "mirrored_placement_id": null, "x": 96, "y": 56},
  {"placement_id": 1507, "mirrored_placement_id": null, "x": 100, "y": 52},
  {"placement_id": 1169, "mirrored_placement_id": null, "x": 96, "y": 48},
  {"placement_id": 1152, "mirrored_placement_id": null, "x": 96, "y": 40},
  {"placement_id": 1489, "mirrored_placement_id": null, "x": 100, "y": 36},
  {"placement_id": 1135, "mirrored_placement_id": null, "x": 96, "y": 32},
  {"placement_id": 1118, "mirrored_placement_id": null, "x": 96, "y": 24},
  {"placement_id": 1471, "mirrored_placement_id": null, "x": 100, "y": 20},
  {"placement_id": 1101, "mirrored_placement_id": null, "x": 96, "y": 16},
  {"placement_id": 1102, "mirrored_placement_id": null, "x": 104, "y": 16},
  {"placement_id": 1119, "mirrored_placement_id": null, "x": 104, "y": 24},
  {"placement_id": 1480, "mirrored_placement_id": null, "x": 108, "y": 28},
  {"placement_id": 1136, "mirrored_placement_id": null, "x": 104, "y": 32},
  {"placement_id": 1153, "mirrored_placement_id": null, "x": 104, "y": 40},
  {"placement_id": 1498, "mirrored_placement_id": null, "x": 108, "y": 44},
  {"placement_id": 1170, "mirrored_placement_id": null, "x": 104, "y": 48},
  {"placement_id": 1187, "mirrored_placement_id": null, "x": 104, "y": 56},
  {"placement_id": 1516, "mirrored_placement_id": null, "x": 108, "y": 60},
  {"placement_id": 1204, "mirrored_placement_id": null, "x": 104, "y": 64},
  {"placement_id": 1221, "mirrored_placement_id": null, "x": 104, "y": 72},
  {"placement_id": 1534, "mirrored_placement_id": null, "x": 108, "y": 76},
  {"placement_id": 1238, "mirrored_placement_id": null, "x": 104, "y": 80},
  {"placement_id": 1255, "mirrored_placement_id": null, "x": 104, "y": 88},
  {"placement_id": 1552, "mirrored_placement_id": null, "x": 108, "y": 92},
  {"placement_id": 1272, "mirrored_placement_id": null, "x": 104, "y": 96},
  {"placement_id": 1289, "mirrored_placement_id": null, "x": 104, "y": 104},
  {"placement_id": 1570, "mirrored_placement_id": null, "x": 108, "y": 108},
  {"placement_id": 1306, "mirrored_placement_id": null, "x": 104, "y": 112},
  {"placement_id": 1323, "mirrored_placement_id": null, "x": 104, "y": 120},
  {"placement_id": 1588, "mirrored_placement_id": null, "x": 108, "y": 124},
  {"placement_id": 1340, "mirrored_placement_id": null, "x": 104, "y": 128},
  {"placement_id": 1357, "mirrored_placement_id": null, "x": 104, "y": 136},
  {"placement_id": 1374, "mirrored_placement_id": null, "x": 104, "y": 144},
  {"placement_id": 1391, "mirrored_placement_id": null, "x": 104, "y": 152},
  {"placement_id": 1408, "mirrored_placement_id": null, "x": 104, "y": 160},
  {"placement_id": 1425, "mirrored_placement_id": null, "x": 104, "y": 168},
  {"placement_id": 1442, "mirrored_placement_id": null, "x": 104, "y": 176},
  {"placement_id": 1443, "mirrored_placement_id": null, "x": 112, "y": 176},
  {"placement_id": 1426, "mirrored_placement_id": null, "x": 112, "y": 168},
  {"placement_id": 1409, "mirrored_placement_id": null, "x": 112, "y": 160},
  {"placement_id": 1392, "mirrored_placement_id": null, "x": 112, "y": 152},
  {"placement_id": 1375, "mirrored_placement_id": null, "x": 112, "y": 144},
  {"placement_id": 1358, "mirrored_placement_id": null, "x": 112, "y": 136},
  {"placement_id": 1598, "mirrored_placement_id": null, "x": 116, "y": 132},
  {"placement_id": 1341, "mirrored_placement_id": null, "x": 112, "y": 128},
  {"placement_id": 1324, "mirrored_placement_id": null, "x": 112, "y": 120},
  {"placement_id": 1580, "mirrored_placement_id": null, "x": 116, "y": 116},
  {"placement_id": 1307, "mirrored_placement_id": null, "x": 112, "y": 112},
  {"placement_id": 1290, "mirrored_placement_id": null, "x": 112, "y": 104},
  {"placement_id": 1562, "mirrored_placement_id": null, "x": 116, "y": 100},
  {"placement_id": 1273, "mirrored_placement_id": null, "x": 112, "y": 96},
  {"placement_id": 1256, "mirrored_placement_id": null, "x": 112, "y": 88},
  {"placement_id": 1544, "mirrored_placement_id": null, "x": 116, "y": 84},
  {"placement_id": 1239, "mirrored_placement_id": null, "x": 112, "y": 80},
  {"placement_id": 1222, "mirrored_placement_id": null, "x": 112, "y": 72},
  {"placement_id": 1526, "mirrored_placement_id": null, "x": 116, "y": 68},
  {"placement_id": 1205, "mirrored_placement_id": null, "x": 112, "y": 64},
  {"placement_id": 1188, "mirrored_placement_id": null, "x": 112, "y": 56},
  {"placement_id": 1508, "mirrored_placement_id": null, "x": 116, "y": 52},
  {"placement_id": 1171, "mirrored_placement_id": null, "x": 112, "y": 48},
  {"placement_id": 1154, "mirrored_placement_id": null, "x": 112, "y": 40},
  {"placement_id": 1490, "mirrored_placement_id": null, "x": 116, "y": 36},
  {"placement_id": 1137, "mirrored_placement_id": null, "x": 112, "y": 32},
  {"placement_id": 1120, "mirrored_placement_id": null, "x": 112, "y": 24},
  {"placement_id": 1472, "mirrored_placement_id": null, "x": 116, "y": 20},
  {"placement_id": 1103, "mirrored_placement_id": null, "x": 112, "y": 16},
  {"placement_id": 1104, "mirrored_placement_id": null, "x": 120, "y": 16},
  {"placement_id": 1121, "mirrored_placement_id": null, "x": 120, "y": 24},
  {"placement_id": 1481, "mirrored_placement_id": null, "x": 124, "y": 28},
  {"placement_id": 1138, "mirrored_placement_id": null, "x": 120, "y": 32},
  {"placement_id": 1155, "mirrored_placement_id": null, "x": 120, "y": 40},
  {"placement_id": 1499, "mirrored_placement_id": null, "x": 124, "y": 44},
  {"placement_id": 1172, "mirrored_placement_id": null, "x": 120, "y": 48},
  {"placement_id": 1189, "mirrored_placement_id": null, "x": 120, "y": 56},
  {"placement_id": 1517, "mirrored_placement_id": null, "x": 124, "y": 60},
  {"placement_id": 1206, "mirrored_placement_id": null, "x": 120, "y": 64},
  {"placement_id": 1223, "mirrored_placement_id": null, "x": 120, "y": 72},
  {"placement_id": 1535, "mirrored_placement_id": null, "x": 124, "y": 76},
  {"placement_id": 1240, "mirrored_placement_id": null, "x": 120, "y": 80},
  {"placement_id": 1257, "mirrored_placement_id": null, "x": 120, "y": 88},
  {"placement_id": 1553, "mirrored_placement_id": null, "x": 124, "y": 92},
  {"placement_id": 1274, "mirrored_placement_id": null, "x": 120, "y": 96},
  {"placement_id": 1291, "mirrored_placement_id": null, "x": 120, "y": 104},
  {"placement_id": 1571, "mirrored_placement_id": null, "x": 124, "y": 108},
  {"placement_id": 1308, "mirrored_placement_id": null, "x": 120, "y": 112},
  {"placement_id": 1325, "mirrored_placement_id": null, "x": 120, "y": 120},
  {"placement_id": 1589, "mirrored_placement_id": null, "x": 124, "y": 124},
  {"placement_id": 1342, "mirrored_placement_id": null, "x": 120, "y": 128},
  {"placement_id": 1359, "mirrored_placement_id": null, "x": 120, "y": 136},
  {"placement_id": 1376, "mirrored_placement_id": null, "x": 120, "y": 144},
  {"placement_id": 1393, "mirrored_placement_id": null, "x": 120, "y": 152},
  {"placement_id": 1410, "mirrored_placement_id": null, "x": 120, "y": 160},
  {"placement_id": 1427, "mirrored_placement_id": null, "x": 120, "y": 168},
  {"placement_id": 1444, "mirrored_placement_id": null, "x": 120, "y": 176},
  {"placement_id": 1445, "mirrored_placement_id": null, "x": 128, "y": 176},
  {"placement_id": 1428, "mirrored_placement_id": null, "x": 128, "y": 168},
  {"placement_id": 1411, "mirrored_placement_id": null, "x": 128, "y": 160},
  {"placement_id": 1394, "mirrored_placement_id": null, "x": 128, "y": 152},
  {"placement_id": 1377, "mirrored_placement_id": null, "x": 128, "y": 144},
  {"placement_id": 1360, "mirrored_placement_id": null, "x": 128, "y": 136},
  {"placement_id": 1599, "mirrored_placement_id": null, "x": 132, "y": 132},
  {"placement_id": 1343, "mirrored_placement_id": null, "x": 128, "y": 128},
  {"placement_id": 1326, "mirrored_placement_id": null, "x": 128, "y": 120},
  {"placement_id": 1581, "mirrored_placement_id": null, "x": 132, "y": 116},
  {"placement_id": 1309, "mirrored_placement_id": null, "x": 128, "y": 112},
  {"placement_id": 1292, "mirrored_placement_id": null, "x": 128, "y": 104},
  {"placement_id": 1563, "mirrored_placement_id": null, "x": 132, "y": 100},
  {"placement_id": 1275, "mirrored_placement_id": null, "x": 128, "y": 96},
  {"placement_id": 1258, "mirrored_placement_id": null, "x": 128, "y": 88},
  {"placement_id": 1545, "mirrored_placement_id": null, "x": 132, "y": 84},
  {"placement_id": 1241, "mirrored_placement_id": null, "x": 128, "y": 80},
  {"placement_id": 1224, "mirrored_placement_id": null, "x": 128, "y": 72},
  {"placement_id": 1527, "mirrored_placement_id": null, "x": 132, "y": 68},
  {"placement_id": 1207, "mirrored_placement_id": null, "x": 128, "y": 64},
  {"placement_id": 1190, "mirrored_placement_id": null, "x": 128, "y": 56},
  {"placement_id": 1509, "mirrored_placement_id": null, "x": 132, "y": 52},
  {"placement_id": 1173, "mirrored_placement_id": null, "x": 128, "y": 48},
  {"placement_id": 1156, "mirrored_placement_id": null, "x": 128, "y": 40},
  {"placement_id": 1491, "mirrored_placement_id": null, "x": 132, "y": 36},
  {"placement_id": 1139, "mirrored_placement_id": null, "x": 128, "y": 32},
  {"placement_id": 1122, "mirrored_placement_id": null, "x": 128, "y": 24},
  {"placement_id": 1473, "mirrored_placement_id": null, "x": 132, "y": 20},
  {"placement_id": 1105, "mirrored_placement_id": null, "x": 128, "y": 16},
  {"placement_id": 1106, "mirrored_placement_id": null, "x": 136, "y": 16},
  {"placement_id": 1123, "mirrored_placement_id": null, "x": 136, "y": 24},
  {"placement_id": 1482, "mirrored_placement_id": null, "x": 140, "y": 28},
  {"placement_id": 1140, "mirrored_placement_id": null, "x": 136, "y": 32},
  {"placement_id": 1157, "mirrored_placement_id": null, "x": 136, "y": 40},
  {"placement_id": 1500, "mirrored_placement_id": null, "x": 140, "y": 44},
  {"placement_id": 1174, "mirrored_placement_id": null, "x": 136, "y": 48},
  {"placement_id": 1191, "mirrored_placement_id": null, "x": 136, "y": 56},
  {"placement_id": 1518, "mirrored_placement_id": null, "x": 140, "y": 60},
  {"placement_id": 1208, "mirrored_placement_id": null, "x": 136, "y": 64},
  {"placement_id": 1225, "mirrored_placement_id": null, "x": 136, "y": 72},
  {"placement_id": 1536, "mirrored_placement_id": null, "x": 140, "y": 76},
  {"placement_id": 1242, "mirrored_placement_id": null, "x": 136, "y": 80},
  {"placement_id": 1259, "mirrored_placement_id": null, "x": 136, "y": 88},
  {"placement_id": 1554, "mirrored_placement_id": null, "x": 140, "y": 92},
  {"placement_id": 1276, "mirrored_placement_id": null, "x": 136, "y": 96},
  {"placement_id": 1293, "mirrored_placement_id": null, "x": 136, "y": 104},
  {"placement_id": 1572, "mirrored_placement_id": null, "x": 140, "y": 108},
  {"placement_id": 1310, "mirrored_placement_id": null, "x": 136, "y": 112},
  {"placement_id": 1327, "mirrored_placement_id": null, "x": 136, "y": 120},
  {"placement_id": 1590, "mirrored_placement_id": null, "x": 140, "y": 124},
  {"placement_id": 1344, "mirrored_placement_id": null, "x": 136, "y": 128},
  {"placement_id": 1361, "mirrored_placement_id": null, "x": 136, "y": 136},
  {"placement_id": 1378, "mirrored_placement_id": null, "x": 136, "y": 144},
  {"placement_id": 1395, "mirrored_placement_id": null, "x": 136, "y": 152},
  {"placement_id": 1412, "mirrored_placement_id": null, "x": 136, "y": 160},
  {"placement_id": 1429, "mirrored_placement_id": null, "x": 136, "y": 168},
  {"placement_id": 1446, "mirrored_placement_id": null, "x": 136, "y": 176},
  {"placement_id": 4681, "mirrored_placement_id": null, "x": 0, "y": 8},
  {"placement_id": 4682, "mirrored_placement_id": null, "x": 0, "y": 16},
  {"placement_id": 4683, "mirrored_placement_id": null, "x": 0, "y": 24},
  {"placement_id": 4684, "mirrored_placement_id": null, "x": 0, "y": 32},
  {"placement_id": 4685, "mirrored_placement_id": null, "x": 0, "y": 40},
  {"placement_id": 4686, "mirrored_placement_id": null, "x": 0, "y": 48},
  {"placement_id": 4687, "mirrored_placement_id": null, "x": 0, "y": 56},
  {"placement_id": 4688, "mirrored_placement_id": null, "x": 0, "y": 64},
  {"placement_id": 4689, "mirrored_placement_id": null, "x": 0, "y": 72},
  {"placement_id": 4690, "mirrored_placement_id": null, "x": 0, "y": 80},
  {"placement_id": 4691, "mirrored_placement_id": null, "x": 0, "y": 88},
  {"placement_id": 4692, "mirrored_placement_id": null, "x": 0, "y": 96},
  {"placement_id": 4693, "mirrored_placement_id": null, "x": 0, "y": 104},
  {"placement_id": 4694, "mirrored_placement_id": null, "x": 0, "y": 112},
  {"placement_id": 4695, "mirrored_placement_id": null, "x": 0, "y": 120},
  {"placement_id": 4696, "mirrored_placement_id": null, "x": 0, "y": 128},
  {"placement_id": 4697, "mirrored_placement_id": null, "x": 0, "y": 136},
  {"placement_id": 4698, "mirrored_placement_id": null, "x": 0, "y": 144},
  {"placement_id": 4699, "mirrored_placement_id": null, "x": 0, "y": 152},
  {"placement_id": 4700, "mirrored_placement_id": null, "x": -8, "y": 8},
  {"placement_id": 4701, "mirrored_placement_id": null, "x": -8, "y": 16},
  {"placement_id": 4702, "mirrored_placement_id": null, "x": -8, "y": 24},
  {"placement_id": 4703, "mirrored_placement_id": null, "x": -8, "y": 32},
  {"placement_id": 4704, "mirrored_placement_id": null, "x": -8, "y": 40},
  {"placement_id": 4705, "mirrored_placement_id": null, "x": -8, "y": 48},
  {"placement_id": 4706, "mirrored_placement_id": null, "x": -8, "y": 56},
  {"placement_id": 4707, "mirrored_placement_id": null, "x": -8, "y": 64},
  {"placement_id": 4708, "mirrored_placement_id": null, "x": -8, "y": 72},
  {"placement_id": 4709, "mirrored_placement_id": null, "x": -8, "y": 80},
  {"placement_id": 4710, "mirrored_placement_id": null, "x": -8, "y": 88},
  {"placement_id": 4711, "mirrored_placement_id": null, "x": -8, "y": 96},
  {"placement_id": 4712, "mirrored_placement_id": null, "x": -8, "y": 104},
  {"placement_id": 4713, "mirrored_placement_id": null, "x": -8, "y": 112},
  {"placement_id": 4714, "mirrored_placement_id": null, "x": -8, "y": 120},
  {"placement_id": 4715, "mirrored_placement_id": null, "x": -8, "y": 128},
  {"placement_id": 4716, "mirrored_placement_id": null, "x": -8, "y": 136},
  {"placement_id": 4717, "mirrored_placement_id": null, "x": -8, "y": 144},
  {"placement_id": 4718, "mirrored_placement_id": null, "x": -8, "y": 152},
  {"placement_id": 4719, "mirrored_placement_id": null, "x": -16, "y": 8},
  {"placement_id": 4720, "mirrored_placement_id": null, "x": -16, "y": 16},
  {"placement_id": 4721, "mirrored_placement_id": null, "x": -16, "y": 24},
  {"placement_id": 4722, "mirrored_placement_id": null, "x": -16, "y": 32},
  {"placement_id": 4723, "mirrored_placement_id": null, "x": -16, "y": 40},
  {"placement_id": 4724, "mirrored_placement_id": null, "x": -16, "y": 48},
  {"placement_id": 4725, "mirrored_placement_id": null, "x": -16, "y": 56},
  {"placement_id": 4726, "mirrored_placement_id": null, "x": -16, "y": 64},
  {"placement_id": 4727, "mirrored_placement_id": null, "x": -16, "y": 72},
  {"placement_id": 4728, "mirrored_placement_id": null, "x": -16, "y": 80},
  {"placement_id": 4729, "mirrored_placement_id": null, "x": -16, "y": 88},
  {"placement_id": 4730, "mirrored_placement_id": null, "x": -16, "y": 96},
  {"placement_id": 4731, "mirrored_placement_id": null, "x": -16, "y": 104},
  {"placement_id": 4732, "mirrored_placement_id": null, "x": -16, "y": 112},
  {"placement_id": 4733, "mirrored_placement_id": null, "x": -16, "y": 120},
  {"placement_id": 4734, "mirrored_placement_id": null, "x": -16, "y": 128},
  {"placement_id": 4735, "mirrored_placement_id": null, "x": -16, "y": 136},
  {"placement_id": 4736, "mirrored_placement_id": null, "x": -16, "y": 144},
  {"placement_id": 4737, "mirrored_placement_id": null, "x": -16, "y": 152},
  {"placement_id": 4738, "mirrored_placement_id": null, "x": 144, "y": 8},
  {"placement_id": 4739, "mirrored_placement_id": null, "x": 144, "y": 16},
  {"placement_id": 4740, "mirrored_placement_id": null, "x": 144, "y": 24},
  {"placement_id": 4741, "mirrored_placement_id": null, "x": 144, "y": 32},
  {"placement_id": 4742, "mirrored_placement_id": null, "x": 144, "y": 40},
  {"placement_id": 4743, "mirrored_placement_id": null, "x": 144, "y": 48},
  {"placement_id": 4744, "mirrored_placement_id": null, "x": 144, "y": 56},
  {"placement_id": 4745, "mirrored_placement_id": null, "x": 144, "y": 64},
  {"placement_id": 4746, "mirrored_placement_id": null, "x": 144, "y": 72},
  {"placement_id": 4747, "mirrored_placement_id": null, "x": 144, "y": 80},
  {"placement_id": 4748, "mirrored_placement_id": null, "x": 144, "y": 88},
  {"placement_id": 4749, "mirrored_placement_id": null, "x": 144, "y": 96},
  {"placement_id": 4750, "mirrored_placement_id": null, "x": 144, "y": 104},
  {"placement_id": 4751, "mirrored_placement_id": null, "x": 144, "y": 112},
  {"placement_id": 4752, "mirrored_placement_id": null, "x": 144, "y": 120},
  {"placement_id": 4753, "mirrored_placement_id": null, "x": 144, "y": 128},
  {"placement_id": 4754, "mirrored_placement_id": null, "x": 144, "y": 136},
  {"placement_id": 4755, "mirrored_placement_id": null, "x": 144, "y": 144},
  {"placement_id": 4756, "mirrored_placement_id": null, "x": 144, "y": 152},
  {"placement_id": 4757, "mirrored_placement_id": null, "x": 152, "y": 8},
  {"placement_id": 4758, "mirrored_placement_id": null, "x": 152, "y": 16},
  {"placement_id": 4759, "mirrored_placement_id": null, "x": 152, "y": 24},
  {"placement_id": 4760, "mirrored_placement_id": null, "x": 152, "y": 32},
  {"placement_id": 4761, "mirrored_placement_id": null, "x": 152, "y": 40},
  {"placement_id": 4762, "mirrored_placement_id": null, "x": 152, "y": 48},
  {"placement_id": 4763, "mirrored_placement_id": null, "x": 152, "y": 56},
  {"placement_id": 4764, "mirrored_placement_id": null, "x": 152, "y": 64},
  {"placement_id": 4765, "mirrored_placement_id": null, "x": 152, "y": 72},
  {"placement_id": 4766, "mirrored_placement_id": null, "x": 152, "y": 80},
  {"placement_id": 4767, "mirrored_placement_id": null, "x": 152, "y": 88},
  {"placement_id": 4768, "mirrored_placement_id": null, "x": 152, "y": 96},
  {"placement_id": 4769, "mirrored_placement_id": null, "x": 152, "y": 104},
  {"placement_id": 4770, "mirrored_placement_id": null, "x": 152, "y": 112},
  {"placement_id": 4771, "mirrored_placement_id": null, "x": 152, "y": 120},
  {"placement_id": 4772, "mirrored_placement_id": null, "x": 152, "y": 128},
  {"placement_id": 4773, "mirrored_placement_id": null, "x": 152, "y": 136},
  {"placement_id": 4774, "mirrored_placement_id": null, "x": 152, "y": 144},
  {"placement_id": 4775, "mirrored_placement_id": null, "x": 152, "y": 152},
  {"placement_id": 4776, "mirrored_placement_id": null, "x": 160, "y": 8},
  {"placement_id": 4777, "mirrored_placement_id": null, "x": 160, "y": 16},
  {"placement_id": 4778, "mirrored_placement_id": null, "x": 160, "y": 24},
  {"placement_id": 4779, "mirrored_placement_id": null, "x": 160, "y": 32},
  {"placement_id": 4780, "mirrored_placement_id": null, "x": 160, "y": 40},
  {"placement_id": 4781, "mirrored_placement_id": null, "x": 160, "y": 48},
  {"placement_id": 4782, "mirrored_placement_id": null, "x": 160, "y": 56},
  {"placement_id": 4783, "mirrored_placement_id": null, "x": 160, "y": 64},
  {"placement_id": 4784, "mirrored_placement_id": null, "x": 160, "y": 72},
  {"placement_id": 4785, "mirrored_placement_id": null, "x": 160, "y": 80},
  {"placement_id": 4786, "mirrored_placement_id": null, "x": 160, "y": 88},
  {"placement_id": 4787, "mirrored_placement_id": null, "x": 160, "y": 96},
  {"placement_id": 4788, "mirrored_placement_id": null, "x": 160, "y": 104},
  {"placement_id": 4789, "mirrored_placement_id": null, "x": 160, "y": 112},
  {"placement_id": 4790, "mirrored_placement_id": null, "x": 160, "y": 120},
  {"placement_id": 4791, "mirrored_placement_id": null, "x": 160, "y": 128},
  {"placement_id": 4792, "mirrored_placement_id": null, "x": 160, "y": 136},
  {"placement_id": 4793, "mirrored_placement_id": null, "x": 160, "y": 144},
  {"placement_id": 4794, "mirrored_placement_id": null, "x": 160, "y": 152},
  {"placement_id": 4795, "mirrored_placement_id": null, "x": -4, "y": 4},
  {"placement_id": 4796, "mirrored_placement_id": null, "x": -12, "y": 4},
  {"placement_id": 4797, "mirrored_placement_id": null, "x": -20, "y": 4},
  {"placement_id": 4798, "mirrored_placement_id": null, "x": 148, "y": 4},
  {"placement_id": 4799, "mirrored_placement_id": null, "x": 156, "y": 4},
  {"placement_id": 4800, "mirrored_placement_id": null, "x": 164, "y": 4},
  {"placement_id": 4801, "mirrored_placement_id": null, "x": -12, "y": 20},
  {"placement_id": 4802, "mirrored_placement_id": null, "x": -20, "y": 28},
  {"placement_id": 4803, "mirrored_placement_id": null, "x": -4, "y": 28},
  {"placement_id": 4804, "mirrored_placement_id": null, "x": -12, "y": 36},
  {"placement_id": 4805, "mirrored_placement_id": null, "x": -20, "y": 44},
  {"placement_id": 4806, "mirrored_placement_id": null, "x": -4, "y": 44},
  {"placement_id": 4807, "mirrored_placement_id": null, "x": -12, "y": 52},
  {"placement_id": 4808, "mirrored_placement_id": null, "x": -20, "y": 60},
  {"placement_id": 4809, "mirrored_placement_id": null, "x": -4, "y": 60},
  {"placement_id": 4810, "mirrored_placement_id": null, "x": -12, "y": 68},
  {"placement_id": 4811, "mirrored_placement_id": null, "x": -20, "y": 76},
  {"placement_id": 4812, "mirrored_placement_id": null, "x": -4, "y": 76},
  {"placement_id": 4813, "mirrored_placement_id": null, "x": -12, "y": 84},
  {"placement_id": 4814, "mirrored_placement_id": null, "x": -20, "y": 92},
  {"placement_id": 4815, "mirrored_placement_id": null, "x": -4, "y": 92},
  {"placement_id": 4816, "mirrored_placement_id": null, "x": -12, "y": 100},
  {"placement_id": 4817, "mirrored_placement_id": null, "x": -20, "y": 108},
  {"placement_id": 4818, "mirrored_placement_id": null, "x": -4, "y": 108},
  {"placement_id": 4819, "mirrored_placement_id": null, "x": -12, "y": 116},
  {"placement_id": 4820, "mirrored_placement_id": null, "x": -20, "y": 124},
  {"placement_id": 4821, "mirrored_placement_id": null, "x": -4, "y": 124},
  {"placement_id": 4822, "mirrored_placement_id": null, "x": -12, "y": 132},
  {"placement_id": 4823, "mirrored_placement_id": null, "x": 148, "y": 20},
  {"placement_id": 4824, "mirrored_placement_id": null, "x": 164, "y": 20},
  {"placement_id": 4825, "mirrored_placement_id": null, "x": 156, "y": 28},
  {"placement_id": 4826, "mirrored_placement_id": null, "x": 148, "y": 36},
  {"placement_id": 4827, "mirrored_placement_id": null, "x": 164, "y": 36},
  {"placement_id": 4828, "mirrored_placement_id": null, "x": 156, "y": 44},
  {"placement_id": 4829, "mirrored_placement_id": null, "x": 148, "y": 52},
  {"placement_id": 4830, "mirrored_placement_id": null, "x": 164, "y": 52},
  {"placement_id": 4831, "mirrored_placement_id": null, "x": 156, "y": 60},
  {"placement_id": 4832, "mirrored_placement_id": null, "x": 148, "y": 68},
  {"placement_id": 4833, "mirrored_placement_id": null, "x": 164, "y": 68},
  {"placement_id": 4834, "mirrored_placement_id": null, "x": 156, "y": 76},
  {"placement_id": 4835, "mirrored_placement_id": null, "x": 148, "y": 84},
  {"placement_id": 4836, "mirrored_placement_id": null, "x": 164, "y": 84},
  {"placement_id": 4837, "mirrored_placement_id": null, "x": 156, "y": 92},
  {"placement_id": 4838, "mirrored_placement_id": null, "x": 148, "y": 100},
  {"placement_id": 4839, "mirrored_placement_id": null, "x": 164, "y": 100},
  {"placement_id": 4840, "mirrored_placement_id": null, "x": 156, "y": 108},
  {"placement_id": 4841, "mirrored_placement_id": null, "x": 148, "y": 116},
  {"placement_id": 4842, "mirrored_placement_id": null, "x": 164, "y": 116},
  {"placement_id": 4843, "mirrored_placement_id": null, "x": 156, "y": 124},
  {"placement_id": 4844, "mirrored_placement_id": null, "x": 148, "y": 132},
  {"placement_id": 4845, "mirrored_placement_id": null, "x": 164, "y": 132}
]